muograph/__init__.py
muograph/analysis/__init__.py
muograph/analysis/analysis.py
muograph/data/iron_barrel/barrel_and_cubes_scattering.csv
muograph/hits/__init__.py
muograph/hits/hits.py
muograph/plotting/__init__.py
muograph/plotting/params.py
muograph/plotting/plotting.py
muograph/plotting/style.py
muograph/plotting/thesis.py
muograph/plotting/voxel.py
muograph/reconstruction/__init__.py
muograph/reconstruction/asr.py
muograph/reconstruction/back_projection.py
muograph/reconstruction/binned_clustered.py
muograph/reconstruction/poca.py
muograph/reconstruction/voxel_inferer.py
muograph/test/__init__.py
muograph/test/test_asr.py
muograph/test/test_bca.py
muograph/test/test_hits.py
muograph/test/test_poca.py
muograph/test/test_tracks.py
muograph/test/test_tracks_mst.py
muograph/tracking/__init__.py
muograph/tracking/tracking.py
muograph/utils/__init__.py
muograph/utils/datatype.py
muograph/utils/device.py
muograph/utils/save.py
muograph/utils/tools.py
muograph/volume/__init__.py
muograph/volume/volume.py
muograph-0.1.22.dist-info/LICENCE
muograph-0.1.22.dist-info/METADATA
muograph-0.1.22.dist-info/WHEEL
muograph-0.1.22.dist-info/RECORD
