Metadata-Version: 2.1
Name: muograph
Version: 0.1.22
Summary: Muon tomography data analysis library
Home-page: https://github.com/MaximeLagrange/muograph
License: AGPL-3.0-only
Keywords: physics,science,statistics,muon tomography,detector simulation
Author: Maxime Lagrange
Author-email: muograph.ml@gmail.com
Requires-Python: >=3.10,<4.0
Classifier: Intended Audience :: Developers
Classifier: Intended Audience :: Science/Research
Classifier: License :: OSI Approved :: GNU Affero General Public License v3
Classifier: Natural Language :: English
Classifier: Programming Language :: Python :: 3
Classifier: Programming Language :: Python :: 3.10
Classifier: Programming Language :: Python :: 3.11
Classifier: Programming Language :: Python :: 3.12
Classifier: Programming Language :: Python :: 3.13
Requires-Dist: awkward
Requires-Dist: fastcore
Requires-Dist: fastprogress
Requires-Dist: h5py
Requires-Dist: pandas
Requires-Dist: scipy
Requires-Dist: seaborn
Requires-Dist: torch (>=2.2.0,<2.4.0)
Requires-Dist: uproot
